collins_client/__init__.py
collins_client/client.py
collins_client-1.0.0.dist-info/METADATA
collins_client-1.0.0.dist-info/WHEEL
collins_client-1.0.0.dist-info/top_level.txt
collins_client-1.0.0.dist-info/RECORD
