Metadata-Version: 2.1
Name: collins-client
Version: 1.0.0
Summary: The python interface to the collins api.
Home-page: https://github.com/tumblr/collins/tree/master/support/python/collins_client
Author: Tumblr Inc.
Author-email: opensourcesoftware@tumblr.com
License: UNKNOWN
Keywords: collins infastructure managment
Platform: UNKNOWN
Classifier: Development Status :: 5 - Production/Stable
Classifier: Intended Audience :: Developers
Classifier: Intended Audience :: System Administrators
Classifier: License :: OSI Approved :: Apache Software License
Classifier: Programming Language :: Python :: 3 :: Only
Classifier: Programming Language :: Python :: 3.6
Classifier: Programming Language :: Python :: 3.7
Classifier: Topic :: System :: Systems Administration
Requires-Dist: grequests (==0.2.0)
